celerator/__init__.py
celerator/app.py
celerator/broker.py
celerator/cli.py
celerator/utils.py
celerator/models/__init__.py
celerator/models/tasks.py
celerator/styles/styles.tcss
celerator/widgets/__init__.py
celerator/widgets/custom_retry_modal.py
celerator-0.1.0.dist-info/licenses/LICENSE
celerator-0.1.0.dist-info/METADATA
celerator-0.1.0.dist-info/WHEEL
celerator-0.1.0.dist-info/entry_points.txt
celerator-0.1.0.dist-info/top_level.txt
celerator-0.1.0.dist-info/RECORD
