Metadata-Version: 2.4
Name: celerator
Version: 0.1.0
Summary: A terminal-based Celery monitoring and debugging tool.
Author-email: Fardin Allahverdi <farih@pm.me>
License-Expression: MIT
License-File: LICENSE
Requires-Dist: celery>=5.5.2
Requires-Dist: textual>=3.2.0
Requires-Dist: rich>=14.0.0
Requires-Dist: redis>=6.0.0
Dynamic: license-file
